resolver/__init__.py
resolver/eks_lb_uri.py
sceptre_eks_lb_resolver-0.2.1.dist-info/LICENSE
sceptre_eks_lb_resolver-0.2.1.dist-info/METADATA
sceptre_eks_lb_resolver-0.2.1.dist-info/WHEEL
sceptre_eks_lb_resolver-0.2.1.dist-info/entry_points.txt
sceptre_eks_lb_resolver-0.2.1.dist-info/top_level.txt
sceptre_eks_lb_resolver-0.2.1.dist-info/RECORD
