Metadata-Version: 2.1
Name: sceptre-eks-lb-resolver
Version: 0.2.1
Summary: A Sceptre resolver to retrieve a kubernetes service load balancer URI
Home-page: https://github.com/pantuza/sceptre-eks-lb-resolver
Author: Gustavo Pantuza
Author-email: gustavopantuza@gmail.com
License: Apache2
Keywords: sceptre,sceptre-resolver,AWS EKS,k8s service load balancer,k8s lb URI,Load Balancer URI,Kubernetes Load Balancer URI,k8s lb dns,k8s service dns
Platform: UNKNOWN
Classifier: Intended Audience :: Developers
Classifier: Natural Language :: English
Classifier: Environment :: Console
Classifier: Programming Language :: Python :: 2.7
Classifier: Programming Language :: Python :: 3.5
Classifier: Programming Language :: Python :: 3.6
Classifier: Programming Language :: Python :: 3.7
Classifier: Programming Language :: Python :: 3.8
Classifier: Programming Language :: Python :: 3.9
Requires-Dist: packaging (==16.8)
Requires-Dist: sceptre (>=2.4.0)
Requires-Dist: kubernetes (>=12.0.1)
Provides-Extra: test
Requires-Dist: pytest (>=3.2) ; extra == 'test'
